ocd/__init__.py
ocd/abc.py
ocd/defaults.py
ocd/deprecate.py
ocd/mixins.py
ocd/prop.py
ocd/types.py
ocd/unro.py
ocd/utils.py
ocd/version.py
ocd/warnings.py
ocd-1.1.3.dist-info/LICENSE
ocd-1.1.3.dist-info/METADATA
ocd-1.1.3.dist-info/WHEEL
ocd-1.1.3.dist-info/top_level.txt
ocd-1.1.3.dist-info/RECORD
