Metadata-Version: 2.1
Name: ocd
Version: 1.1.3
Summary: Convert class attributes to properties easily and automatically and more
Home-page: https://github.com/neurobin/python-ocd
Author: Md. Jahidul Hamid
Author-email: jahidulhamid@yahoo.com
License: BSD
Keywords: property auto attributes
Platform: UNKNOWN
Classifier: Development Status :: 5 - Production/Stable
Classifier: Intended Audience :: Developers
Classifier: Intended Audience :: Information Technology
Classifier: License :: OSI Approved :: BSD License
Classifier: Operating System :: OS Independent
Classifier: Programming Language :: Python
Classifier: Programming Language :: Python :: 3
Requires-Dist: packaging
